brickworks/__init__.py
brickworks/py.typed
brickworks/core/__init__.py
brickworks/core/alembic.ini
brickworks/core/brick.json
brickworks/core/cache.py
brickworks/core/constants.py
brickworks/core/db.py
brickworks/core/exceptions.py
brickworks/core/module_loader.py
brickworks/core/server.py
brickworks/core/settings.py
brickworks/core/signals.py
brickworks/core/acl/__init__.py
brickworks/core/acl/base_policy.py
brickworks/core/acl/policies.py
brickworks/core/auth/__init__.py
brickworks/core/auth/csrf.py
brickworks/core/auth/executioncontext.py
brickworks/core/auth/jwt.py
brickworks/core/auth/oidc.py
brickworks/core/auth/session.py
brickworks/core/migration/env.py
brickworks/core/migration/script.py.mako
brickworks/core/models/__init__.py
brickworks/core/models/base_dbmodel.py
brickworks/core/models/base_view.py
brickworks/core/models/file_model.py
brickworks/core/models/mixins.py
brickworks/core/models/role_model.py
brickworks/core/models/tenant_model.py
brickworks/core/models/user_model.py
brickworks/core/routers/__init__.py
brickworks/core/routers/auth_router.py
brickworks/core/schemas/__init__.py
brickworks/core/schemas/auth_schemas.py
brickworks/core/schemas/base_schema.py
brickworks/core/utils/__init__.py
brickworks/core/utils/importer.py
brickworks/core/utils/sqlalchemy.py
brickworks/core/utils/timeutils.py
brickworks/mason/__init__.py
brickworks/mason/__main__.py
brickworks/mason/brick_app.py
brickworks/mason/db_app.py
brickworks-0.0.9.dist-info/licenses/LICENCE
brickworks-0.0.9.dist-info/METADATA
brickworks-0.0.9.dist-info/WHEEL
brickworks-0.0.9.dist-info/entry_points.txt
brickworks-0.0.9.dist-info/top_level.txt
brickworks-0.0.9.dist-info/RECORD
