Metadata-Version: 2.4
Name: brickworks
Version: 0.0.9
Summary: A highly opinionated framework based on FastAPI and Sqlalchemy.
Requires-Python: >=3.11
License-File: LICENCE
Requires-Dist: aiohttp>=3.11.18
Requires-Dist: alembic>=1.15.2
Requires-Dist: asyncpg>=0.30.0
Requires-Dist: fastapi>=0.115.12
Requires-Dist: pydantic-settings>=2.9.1
Requires-Dist: redis>=6.0.0
Requires-Dist: sqlalchemy>=2.0.40
Requires-Dist: tomli>=2.2.1
Requires-Dist: tomli-w>=1.2.0
Requires-Dist: typer>=0.16.0
Requires-Dist: uvicorn>=0.34.2
Requires-Dist: click>=8.0.0
Requires-Dist: itsdangerous>=2.2.0
Requires-Dist: authlib>=1.5.2
Requires-Dist: email-validator>=2.2.0
Requires-Dist: pyjwt>=2.10.1
Requires-Dist: httpx>=0.27.2
Dynamic: license-file
